conf.py
mirror_api/__init__.py
mirror_api/__main__.py
mirror_api/_app_entrypoint.py
mirror_api/_router.py
mirror_api/_settings.py
mirror_api/app.py
mirror_api/reflected_response.py
version.py
mirror_api-1.4.0.dist-info/entry_points.txt
mirror_api-1.4.0.dist-info/WHEEL
mirror_api-1.4.0.dist-info/LICENSE.md
mirror_api-1.4.0.dist-info/METADATA
mirror_api-1.4.0.dist-info/RECORD
