Metadata-Version: 2.1
Name: mirror-api
Version: 1.4.0
Summary: An API that returns the structure of the request as the response
License: MIT
Author: Nick DeRobertis
Author-email: derobertis.nick@gmail.com
Requires-Python: >=3.8
Classifier: Development Status :: 3 - Alpha
Classifier: Intended Audience :: Developers
Classifier: License :: OSI Approved :: MIT License
Classifier: Programming Language :: Python :: 3
Classifier: Programming Language :: Python :: 3.8
Classifier: Programming Language :: Python :: 3.9
Classifier: Programming Language :: Python :: 3.10
Classifier: Programming Language :: Python :: 3.11
Classifier: Programming Language :: Python :: 3.10
Classifier: Programming Language :: Python :: 3.11
Classifier: Programming Language :: Python :: 3.7
Classifier: Programming Language :: Python :: 3.8
Classifier: Programming Language :: Python :: 3.9
Requires-Dist: fastapi
Requires-Dist: python-multipart
Requires-Dist: typer
Requires-Dist: uvicorn[standard]
Project-URL: documentation, https://nickderobertis.github.io/mirror-api
Project-URL: repository, https://github.com/nickderobertis/mirror-api
